{
  "id": "futures",
  "name": "大宗贸易期货专家",
  "icon": "icon-futures",
  "color": "#FF5722",
  "fields": [
    { "id": "energy", "name": "能源化工", "icon": "⚡" },
    { "id": "metal", "name": "金属矿产", "icon": "🔩" },
    { "id": "agricultural", "name": "农产品", "icon": "🌾" },
    { "id": "soft", "name": "软商品", "icon": "☕" },
    { "id": "analysis", "name": "行情分析", "icon": "📊" }
  ],
  "version": "1.0.0",
  "updated": "2026-04-16",
  "fallback": [
    { "title": "原油期货交易基础", "category": "能源化工", "categoryIcon": "⚡", "content": "原油期货是最重要的能源类期货品种之一，主要包括WTI原油和布伦特原油。交易原油期货需要关注地缘政治、OPEC产能、库存数据等因素。WTI原油在纽约商品交易所交易，布伦特原油在伦敦洲际交易所交易。", "subtitle": "能源期货入门" },
    { "title": "黄金期货投资策略", "category": "金属矿产", "categoryIcon": "🔩", "content": "黄金作为避险资产，其期货价格受美元走势、通胀预期、地缘政治等因素影响。COMEX黄金是全球最大的黄金期货市场。投资者常使用黄金对冲通胀风险和股市波动风险。", "subtitle": "避险资产配置" },
    { "title": "大豆期货产业链分析", "category": "农产品", "categoryIcon": "🌾", "content": "大豆期货是重要的农产品期货，涉及CBOT大豆和国内豆粕、豆油合约。影响大豆价格的因素包括南美产量、美国种植面积、天气变化、中国采购需求等。", "subtitle": "农产品期货" },
    { "title": "铜期货的宏观经济属性", "category": "金属矿产", "categoryIcon": "🔩", "content": "铜被称为'经济晴雨表'，因其与宏观经济走势高度相关。铜期货交易需关注全球制造业PMI、房地产数据、新能源需求等因素。COMEX铜是全球铜定价的重要参考。", "subtitle": "铜博士指标" },
    { "title": "天然气期货季节性规律", "category": "能源化工", "categoryIcon": "⚡", "content": "天然气期货价格呈现明显的季节性特征，冬季取暖需求推高价格，夏季发电需求次之。页岩气产量、LNG出口、库存水平是影响天然气价格的关键因素。", "subtitle": "能源季节波动" },
    { "title": "棉花期货贸易要点", "category": "农产品", "categoryIcon": "🌾", "content": "棉花期货是软商品代表品种之一，受全球棉花产量、纺织需求、贸易政策等因素影响。美国、印度、中国是主要棉花生产国，郑州商品交易所是国内棉花期货交易场所。", "subtitle": "纺织原料期货" },
    { "title": "铁矿石期货定价机制", "category": "金属矿产", "categoryIcon": "🔩", "content": "铁矿石是钢铁生产的主要原料，大商所铁矿石期货已成为全球成交最活跃的铁矿石衍生品。钢铁产量、港口库存、四大矿山发货量是影响铁矿石价格的核心因素。", "subtitle": "黑色系核心品种" },
    { "title": "白糖期货基本面分析", "category": "农产品", "categoryIcon": "🌾", "content": "白糖期货涉及原糖（ICE）和国内白糖期货（郑商所）。巴西、印度、泰国是主要产糖国，甘蔗和甜菜是主要原料。全球食糖供需平衡表是判断价格走势的重要依据。", "subtitle": "甜蜜期货品种" },
    { "title": "甲醇期货产业链", "category": "能源化工", "categoryIcon": "⚡", "content": "甲醇是重要的化工原料，郑商所甲醇期货反映国内甲醇市场供需状况。甲醇上游为煤炭和天然气，下游用于烯烃、甲醛等化工产品。能耗双控政策对甲醇供应影响显著。", "subtitle": "化工品期货" },
    { "title": "橡胶期货投资逻辑", "category": "农产品", "categoryIcon": "🌾", "content": "天然橡胶期货在上期所和日胶市场交易。橡胶价格受汽车产销、轮胎需求、天胶产区天气等因素影响。东南亚是主要橡胶产区，泰国、印尼、越南产量占全球大半。", "subtitle": "工业基础原料" }
  ],
  "share": {
    "title": "大宗贸易期货专家",
    "template": "{content}"
  }
}
